sfeos_tools/__init__.py
sfeos_tools/bbox_shape.py
sfeos_tools/cli.py
sfeos_tools/data_loader.py
sfeos_tools/reindex.py
sfeos_tools/viewer.py
sfeos_tools-0.3.0.dist-info/licenses/LICENSE
sfeos_tools-0.3.0.dist-info/METADATA
sfeos_tools-0.3.0.dist-info/WHEEL
sfeos_tools-0.3.0.dist-info/entry_points.txt
sfeos_tools-0.3.0.dist-info/top_level.txt
sfeos_tools-0.3.0.dist-info/RECORD
