Metadata-Version: 2.4
Name: sfeos-tools
Version: 0.3.0
Summary: CLI tools for managing stac-fastapi-elasticsearch-opensearch deployments
Author: CloudFerro S.A., Healy Hyperspatial
Author-email: Jonathan Healy <jon@healy-hypersaptial.dev>
Maintainer-email: Jonathan Healy <jon@healy-hypersaptial.dev>
License: MIT License
Project-URL: Homepage, https://github.com/Healy-Hyperspatial/sfeos-tools
Project-URL: Documentation, https://github.com/Healy-Hyperspatial/sfeos-tools#readme
Project-URL: Issues, https://github.com/Healy-Hyperspatial/sfeos-tools/issues
Project-URL: Source, https://github.com/Healy-Hyperspatial/sfeos-tools
Classifier: Development Status :: 4 - Beta
Classifier: Intended Audience :: Developers
Classifier: Intended Audience :: Science/Research
Classifier: License :: OSI Approved :: MIT License
Classifier: Programming Language :: Python :: 3.9
Classifier: Programming Language :: Python :: 3.10
Classifier: Programming Language :: Python :: 3.11
Classifier: Programming Language :: Python :: 3.12
Classifier: Programming Language :: Python :: 3.13
Classifier: Programming Language :: Python :: 3.14
Classifier: Topic :: Scientific/Engineering
Classifier: Topic :: Scientific/Engineering :: GIS
Classifier: Topic :: Software Development :: Libraries :: Python Modules
Requires-Python: >=3.8
License-File: LICENSE
Requires-Dist: click>=8.0.0
Requires-Dist: httpx>=0.24.0
Requires-Dist: orjson>=3.0.0
Provides-Extra: elasticsearch
Requires-Dist: stac-fastapi-elasticsearch>=6.6.0; extra == "elasticsearch"
Provides-Extra: opensearch
Requires-Dist: stac-fastapi-opensearch>=6.6.0; extra == "opensearch"
Provides-Extra: viewer
Requires-Dist: streamlit>=1.28.0; extra == "viewer"
Requires-Dist: folium>=0.14.0; extra == "viewer"
Requires-Dist: streamlit-folium>=0.15.0; extra == "viewer"
Requires-Dist: pillow>=9.0.0; extra == "viewer"
Provides-Extra: dev
Requires-Dist: stac-fastapi-elasticsearch>=6.6.0; extra == "dev"
Requires-Dist: stac-fastapi-opensearch>=6.6.0; extra == "dev"
Requires-Dist: streamlit>=1.28.0; extra == "dev"
Requires-Dist: folium>=0.14.0; extra == "dev"
Requires-Dist: streamlit-folium>=0.15.0; extra == "dev"
Requires-Dist: pillow>=9.0.0; extra == "dev"
Requires-Dist: pytest>=6.0; extra == "dev"
Requires-Dist: pytest-asyncio>=0.21.0; extra == "dev"
Requires-Dist: pytest-cov>=2.0; extra == "dev"
Requires-Dist: black>=21.0; extra == "dev"
Requires-Dist: isort>=5.0; extra == "dev"
Requires-Dist: mypy>=0.900; extra == "dev"
Requires-Dist: flake8>=4.0.0; extra == "dev"
Dynamic: license-file
